redmine_mcp_server/__init__.py
redmine_mcp_server/file_manager.py
redmine_mcp_server/main.py
redmine_mcp_server/redmine_handler.py
redmine_mcp_server-0.10.0.dist-info/METADATA
redmine_mcp_server-0.10.0.dist-info/WHEEL
redmine_mcp_server-0.10.0.dist-info/entry_points.txt
redmine_mcp_server-0.10.0.dist-info/licenses/LICENSE
redmine_mcp_server-0.10.0.dist-info/RECORD
