Metadata-Version: 2.4
Name: redmine-mcp-server
Version: 0.10.0
Summary: Production-ready MCP server for Redmine with security, pagination, and enterprise features
Project-URL: Homepage, https://github.com/jztan/redmine-mcp-server
Project-URL: Repository, https://github.com/jztan/redmine-mcp-server.git
Project-URL: Issues, https://github.com/jztan/redmine-mcp-server/issues
Project-URL: Changelog, https://github.com/jztan/redmine-mcp-server/blob/master/CHANGELOG.md
Author-email: Kevin Tan <jingzheng.tan@gmail.com>
Maintainer-email: Kevin Tan <jingzheng.tan@gmail.com>
License: MIT
License-File: LICENSE
Keywords: mcp,model-context-protocol,project-management,redmine,server
Classifier: Development Status :: 4 - Beta
Classifier: Intended Audience :: Developers
Classifier: License :: OSI Approved :: MIT License
Classifier: Programming Language :: Python :: 3
Classifier: Programming Language :: Python :: 3.10
Classifier: Programming Language :: Python :: 3.11
Classifier: Programming Language :: Python :: 3.12
Classifier: Programming Language :: Python :: 3.13
Classifier: Topic :: Office/Business :: Groupware
Classifier: Topic :: Software Development :: Libraries :: Python Modules
Requires-Python: >=3.10
Requires-Dist: fastapi[standard]>=0.120.0
Requires-Dist: mcp[cli]<2,>=1.25.0
Requires-Dist: python-dotenv>=1.0.0
Requires-Dist: python-redmine>=2.5.0
Requires-Dist: uvicorn>=0.24.0
Provides-Extra: dev
Requires-Dist: black>=23.0.0; extra == 'dev'
Requires-Dist: flake8>=6.0.0; extra == 'dev'
Requires-Dist: httpx>=0.28.1; extra == 'dev'
Requires-Dist: pytest-asyncio>=0.21.0; extra == 'dev'
Requires-Dist: pytest-cov>=4.0.0; extra == 'dev'
Requires-Dist: pytest-mock>=3.10.0; extra == 'dev'
Requires-Dist: pytest>=7.0.0; extra == 'dev'
Provides-Extra: test
Requires-Dist: httpx>=0.28.1; extra == 'test'
Requires-Dist: pytest-asyncio>=0.21.0; extra == 'test'
Requires-Dist: pytest-cov>=4.0.0; extra == 'test'
Requires-Dist: pytest-mock>=3.10.0; extra == 'test'
Requires-Dist: pytest>=7.0.0; extra == 'test'
